MANIFEST.in
README.rst
setup.py
boatd_client/__init__.py
boatd_client/boatd_client.py
boatd_client/markdown_doc.py
boatd_client.egg-info/PKG-INFO
boatd_client.egg-info/SOURCES.txt
boatd_client.egg-info/dependency_links.txt
boatd_client.egg-info/requires.txt
boatd_client.egg-info/top_level.txt