Metadata-Version: 1.1
Name: boatd-client
Version: 0.1.5
Summary: Python wrapper for the boatd API, used to write behavior scripts.
Home-page: https://github.com/boatd/python-boatd
Author: Louis Taylor
Author-email: kragniz@gmail.com
License: GPL
Keywords: boat sailing wrapper rest
Platform: UNKNOWN
Classifier: Development Status :: 3 - Alpha
Classifier: Intended Audience :: Developers
Classifier: Topic :: Software Development :: Libraries :: Python Modules
Classifier: License :: OSI Approved :: GNU General Public License v3 (GPLv3)
Requires: docopt
